shadwell/__init__.py
shadwell/candidate.py
shadwell/finder.py
shadwell/sources/__init__.py
shadwell/sources/json_api.py
shadwell-0.1.dist-info/LICENSE.txt
shadwell-0.1.dist-info/METADATA
shadwell-0.1.dist-info/WHEEL
shadwell-0.1.dist-info/top_level.txt
shadwell-0.1.dist-info/RECORD
