Metadata-Version: 2.1
Name: shadwell
Version: 0.1
Summary: A package finder library for Python
Home-page: https://github.com/pfmoore/shadwell
Author: Paul Moore
Author-email: p.f.moore@gmail.com
Maintainer: Paul Moore
Maintainer-email: p.f.moore@gmail.com
License: MIT
Project-URL: Source, https://github.com/pfmoore/shadwell
Project-URL: Tracker, https://github.com/pfmoore/shadwell/issues
Keywords: packaging
Platform: any
Classifier: Development Status :: 5 - Production/Stable
Classifier: Intended Audience :: Developers
Classifier: License :: OSI Approved :: MIT License
Classifier: Programming Language :: Python :: 3
Classifier: Programming Language :: Python :: 3 :: Only
Classifier: Programming Language :: Python :: 3.5
Classifier: Programming Language :: Python :: 3.6
Classifier: Programming Language :: Python :: 3.7
Classifier: Programming Language :: Python :: 3.8
Classifier: Programming Language :: Python :: 3.9
Classifier: Programming Language :: Python :: Implementation :: CPython
Classifier: Programming Language :: Python :: Implementation :: PyPy
Classifier: Topic :: Software Development :: Libraries
Classifier: Topic :: Utilities
Requires-Python: >=3.5
Provides-Extra: test
Requires-Dist: pytest (>=4) ; extra == 'test'
Requires-Dist: virtualenv (>=20) ; extra == 'test'
